deepfacesnap/DeepFace.py
deepfacesnap/__init__.py
deepfacesnap/api/__init__.py
deepfacesnap/api/src/__init__.py
deepfacesnap/api/src/api.py
deepfacesnap/api/src/app.py
deepfacesnap/api/src/modules/__init__.py
deepfacesnap/api/src/modules/core/__init__.py
deepfacesnap/api/src/modules/core/routes.py
deepfacesnap/api/src/modules/core/service.py
deepfacesnap/basemodels/ArcFace.py
deepfacesnap/basemodels/DeepID.py
deepfacesnap/basemodels/Dlib.py
deepfacesnap/basemodels/Facenet.py
deepfacesnap/basemodels/FbDeepFace.py
deepfacesnap/basemodels/OpenFace.py
deepfacesnap/basemodels/SFace.py
deepfacesnap/basemodels/VGGFace.py
deepfacesnap/basemodels/__init__.py
deepfacesnap/commons/__init__.py
deepfacesnap/commons/constant.py
deepfacesnap/commons/folder_utils.py
deepfacesnap/commons/logger.py
deepfacesnap/commons/package_utils.py
deepfacesnap/detectors/DetectorWrapper.py
deepfacesnap/detectors/Dlib.py
deepfacesnap/detectors/FastMtCnn.py
deepfacesnap/detectors/MediaPipe.py
deepfacesnap/detectors/MtCnn.py
deepfacesnap/detectors/OpenCv.py
deepfacesnap/detectors/RetinaFace.py
deepfacesnap/detectors/Ssd.py
deepfacesnap/detectors/Yolo.py
deepfacesnap/detectors/YuNet.py
deepfacesnap/detectors/__init__.py
deepfacesnap/extendedmodels/Age.py
deepfacesnap/extendedmodels/Emotion.py
deepfacesnap/extendedmodels/Gender.py
deepfacesnap/extendedmodels/Race.py
deepfacesnap/extendedmodels/__init__.py
deepfacesnap/models/Demography.py
deepfacesnap/models/Detector.py
deepfacesnap/models/FacialRecognition.py
deepfacesnap/models/__init__.py
deepfacesnap/modules/__init__.py
deepfacesnap/modules/demography.py
deepfacesnap/modules/detection.py
deepfacesnap/modules/modeling.py
deepfacesnap/modules/preprocessing.py
deepfacesnap/modules/realtime.py
deepfacesnap/modules/recognition.py
deepfacesnap/modules/representation.py
deepfacesnap/modules/verification.py
deepfacesnap-0.0.2.data/data/README.md
deepfacesnap-0.0.2.data/data/package_info.json
deepfacesnap-0.0.2.data/data/requirements.txt
deepfacesnap-0.0.2.dist-info/LICENSE
deepfacesnap-0.0.2.dist-info/METADATA
deepfacesnap-0.0.2.dist-info/WHEEL
deepfacesnap-0.0.2.dist-info/entry_points.txt
deepfacesnap-0.0.2.dist-info/top_level.txt
deepfacesnap-0.0.2.dist-info/RECORD
